resiliens/__init__.py
resiliens/circuit_breaker/CircuitBreaker.py
resiliens/circuit_breaker/CircuitBreakerException.py
resiliens/circuit_breaker/CircuitBreakerState.py
resiliens/circuit_breaker/CircuitBreakerStatus.py
resiliens/circuit_breaker/SlidingWindow.py
resiliens/circuit_breaker/__init__.py
resiliens/circuit_breaker/manager/CircuitBreakerManager.py
resiliens/circuit_breaker/manager/__init__.py
resiliens/fallback/Fallback.py
resiliens/fallback/__init__.py
resiliens/retryable/Retryable.py
resiliens/retryable/__init__.py
Resiliens-0.0.10.dist-info/METADATA
Resiliens-0.0.10.dist-info/WHEEL
Resiliens-0.0.10.dist-info/top_level.txt
Resiliens-0.0.10.dist-info/RECORD
