Metadata-Version: 2.1
Name: Resiliens
Version: 0.0.10
Summary: A Python package for resilient programming.
Home-page: https://github.com/jonmest/resiliens
Author: Jon Cavallie Mester
Author-email: jwcavalliemester@protonmail.com
License: UNKNOWN
Project-URL: Bug Tracker, https://github.com/jonmest/resiliens/issues
Platform: UNKNOWN
Classifier: Programming Language :: Python :: 3
Classifier: License :: OSI Approved :: GNU General Public License v3 or later (GPLv3+)
Classifier: Operating System :: OS Independent
Requires-Python: >=3.6
